mipi_env_manager/_main.py
mipi_env_manager/main.py
mipi_env_manager/templates/env_installer.bat.jinja
mipi_env_manager/templates/master_installer.bat.jinja
mipi_env_manager-0.3.0.dist-info/entry_points.txt
mipi_env_manager-0.3.0.dist-info/METADATA
mipi_env_manager-0.3.0.dist-info/WHEEL
mipi_env_manager-0.3.0.dist-info/RECORD
