Metadata-Version: 2.1
Name: mipi_env_manager
Version: 0.3.0
Summary: 
Author: Sean Murphy
Author-email: murphy-sean1@cooperhealth.edu
Requires-Python: >=3.12,<4.0
Classifier: Programming Language :: Python :: 3
Classifier: Programming Language :: Python :: 3.12
Requires-Dist: click (>=8.1.8,<9.0.0)
Requires-Dist: jinja2 (>=3.1.5,<4.0.0)
Requires-Dist: packaging (>=24.2,<25.0)
Requires-Dist: pytest (>=8.3.4,<9.0.0)
Requires-Dist: pytest-cov (>=6.0.0,<7.0.0)
Requires-Dist: pyyaml (>=6.0.2,<7.0.0)
Requires-Dist: requests (>=2.32.3,<3.0.0)
